omd_emea/__init__.py
omd_emea/apis/__init__.py
omd_emea/apis/adverity_api.py
omd_emea/apis/facebook_api.py
omd_emea/general/__init__.py
omd_emea/general/general_functions.py
omd_emea/taxonomy_field_checker/__init__.py
omd_emea/taxonomy_field_checker/taxonomy_field_checker.py
omd_emea-0.1.9.dist-info/METADATA
omd_emea-0.1.9.dist-info/WHEEL
omd_emea-0.1.9.dist-info/top_level.txt
omd_emea-0.1.9.dist-info/RECORD
