Metadata-Version: 2.1
Name: omd-emea
Version: 0.1.9
Summary: Generic code for processing and execution for OMD EMEA
Home-page: UNKNOWN
Author: Aniruddha Sengupta
Author-email: aniruddha.sengupta@omd.com
License: UNKNOWN
Keywords: python,omd,general,generic
Platform: UNKNOWN
Classifier: Development Status :: 1 - Planning
Classifier: Intended Audience :: Developers
Classifier: Programming Language :: Python :: 3
Classifier: Operating System :: Unix
Classifier: Operating System :: MacOS :: MacOS X
Classifier: Operating System :: Microsoft :: Windows
Requires-Dist: requests
Requires-Dist: pandas
Requires-Dist: facebook-business
Requires-Dist: google
Requires-Dist: google-api-python-client
Requires-Dist: google-cloud
Requires-Dist: google-cloud-storage
Requires-Dist: google-cloud-bigquery-storage
Requires-Dist: sqlalchemy
Requires-Dist: selenium
